LICENSE
MANIFEST.in
README.md
pyproject.toml
setup.cfg
setup.py
versioneer.py
msgspec/__init__.py
msgspec/__init__.pyi
msgspec/_core.c
msgspec/_json_schema.py
msgspec/_utils.py
msgspec/_version.py
msgspec/atof.h
msgspec/atof_consts.h
msgspec/common.h
msgspec/inspect.py
msgspec/itoa.h
msgspec/json.py
msgspec/json.pyi
msgspec/msgpack.py
msgspec/msgpack.pyi
msgspec/py.typed
msgspec/ryu.h
msgspec/structs.py
msgspec/structs.pyi
msgspec/toml.py
msgspec/yaml.py
msgspec_fuf.egg-info/PKG-INFO
msgspec_fuf.egg-info/SOURCES.txt
msgspec_fuf.egg-info/dependency_links.txt
msgspec_fuf.egg-info/not-zip-safe
msgspec_fuf.egg-info/requires.txt
msgspec_fuf.egg-info/top_level.txt