Metadata-Version: 2.1
Name: msgspec-fuf
Version: 0.19.0
Summary: A fast serialization and validation library, with builtin support for JSON, MessagePack, YAML, and TOML. Forked for forbid_unknown_feature support.
Home-page: https://github.com/eamartin/msgspec/
Maintainer: Eric Martin
License: BSD
Project-URL: Documentation, https://jcristharif.com/msgspec/
Project-URL: Source, https://github.com/eamartin/msgspec/
Keywords: JSON msgpack MessagePack TOML YAML serialization validation schema
Platform: UNKNOWN
Classifier: License :: OSI Approved :: BSD License
Classifier: Development Status :: 4 - Beta
Classifier: Programming Language :: Python :: 3.9
Classifier: Programming Language :: Python :: 3.10
Classifier: Programming Language :: Python :: 3.11
Classifier: Programming Language :: Python :: 3.12
Classifier: Programming Language :: Python :: 3.13
Requires-Python: >=3.9
Provides-Extra: dev
Provides-Extra: doc
Provides-Extra: test
Provides-Extra: toml
Provides-Extra: yaml
License-File: LICENSE
